ephemeral_notebooks/__init__.py
ephemeral_notebooks/_version 2.py
ephemeral_notebooks/_version.py
ephemeral_notebooks-0.3.43.data/data/share/jupyter/labextensions/ephemeral-notebooks/package.json
ephemeral_notebooks-0.3.43.data/data/share/jupyter/labextensions/ephemeral-notebooks/static/345.d894eb52f2d0d270fb46.js
ephemeral_notebooks-0.3.43.data/data/share/jupyter/labextensions/ephemeral-notebooks/static/728.1ee4c410a2669ff0e7d0.js
ephemeral_notebooks-0.3.43.data/data/share/jupyter/labextensions/ephemeral-notebooks/static/992.4d546316b7bbec7c9f7c.js
ephemeral_notebooks-0.3.43.data/data/share/jupyter/labextensions/ephemeral-notebooks/static/remoteEntry.60af0a862b4f0bea0944.js
ephemeral_notebooks-0.3.43.data/data/share/jupyter/labextensions/ephemeral-notebooks/static/style.js
ephemeral_notebooks-0.3.43.data/data/share/jupyter/labextensions/ephemeral-notebooks/static/third-party-licenses.json
ephemeral_notebooks-0.3.43.data/data/share/jupyter/labextensions/ephemeral-notebooks/install.json
ephemeral_notebooks-0.3.43.dist-info/METADATA
ephemeral_notebooks-0.3.43.dist-info/WHEEL
ephemeral_notebooks-0.3.43.dist-info/licenses/LICENSE
ephemeral_notebooks-0.3.43.dist-info/RECORD
