Metadata-Version: 2.3
Name: ephemeral_notebooks
Version: 0.3.43
Dynamic: Keywords
Summary: Extension for creating jupyter notebooks from urls.
Project-URL: Homepage, https://github.com/github_username/ephemeral-notebooks
Project-URL: Bug Tracker, https://github.com/github_username/ephemeral-notebooks/issues
Project-URL: Repository, https://github.com/github_username/ephemeral-notebooks.git
Author-email: Dylan Wootton <wootton.dylan@gmail.com>
License: BSD 3-Clause License
License-File: LICENSE
Classifier: Framework :: Jupyter
Classifier: Framework :: Jupyter :: JupyterLab
Classifier: Framework :: Jupyter :: JupyterLab :: 4
Classifier: Framework :: Jupyter :: JupyterLab :: Extensions
Classifier: Framework :: Jupyter :: JupyterLab :: Extensions :: Prebuilt
Classifier: License :: OSI Approved :: BSD License
Classifier: Programming Language :: Python
Classifier: Programming Language :: Python :: 3
Classifier: Programming Language :: Python :: 3.8
Classifier: Programming Language :: Python :: 3.9
Classifier: Programming Language :: Python :: 3.10
Classifier: Programming Language :: Python :: 3.11
Requires-Python: >=3.8
